clr.py
pythonnet/__init__.py
pythonnet/runtime/Python.Runtime.deps.json
pythonnet/runtime/Python.Runtime.dll
pythonnet/runtime/Python.Runtime.pdb
pythonnet/runtime/Python.Runtime.xml
ansys_pythonnet-3.1.0rc7.dist-info/METADATA
ansys_pythonnet-3.1.0rc7.dist-info/WHEEL
ansys_pythonnet-3.1.0rc7.dist-info/top_level.txt
ansys_pythonnet-3.1.0rc7.dist-info/RECORD
