Metadata-Version: 2.2
Name: ansys-pythonnet
Version: 3.1.0rc7
Summary: .NET and Mono integration for Python (Ansys, Inc. fork)
Author-email: "ANSYS, Inc." <pyansys.maintainers@ansys.com>
License: MIT
Project-URL: Homepage, https://github.com/pyansys/ansys-pythonnet
Project-URL: Sources, https://github.com/pyansys/ansys-pythonnet
Classifier: Development Status :: 5 - Production/Stable
Classifier: Intended Audience :: Developers
Classifier: License :: OSI Approved :: MIT License
Classifier: Programming Language :: C#
Classifier: Programming Language :: Python :: 3
Classifier: Programming Language :: Python :: 3.7
Classifier: Programming Language :: Python :: 3.8
Classifier: Programming Language :: Python :: 3.9
Classifier: Programming Language :: Python :: 3.10
Classifier: Programming Language :: Python :: 3.11
Classifier: Programming Language :: Python :: 3.12
Classifier: Programming Language :: Python :: 3.13
Classifier: Operating System :: Microsoft :: Windows
Classifier: Operating System :: POSIX :: Linux
Classifier: Operating System :: MacOS :: MacOS X
Requires-Python: <3.14,>=3.7
Requires-Dist: clr_loader<0.3.0,>=0.2.5
